
BEGIN_MAPPING(Opcode,Java::u1)
INSERT(nop,0x00)
INSERT(aconst_null,0x01)
INSERT(iconst_m1,0x02)
INSERT(iconst_0,0x03)
INSERT(iconst_1,0x04)
INSERT(iconst_2,0x05)
INSERT(iconst_3,0x06)
INSERT(iconst_4,0x07)
INSERT(iconst_5,0x08)
INSERT(lconst_0,0x09)
INSERT(lconst_1,0x0a)
INSERT(fconst_0,0x0b)
INSERT(fconst_1,0x0c)
INSERT(fconst_2,0x0d)
INSERT(dconst_0,0x0e)
INSERT(dconst_1,0x0f)
INSERT(bipush,0x10)
INSERT(sipush,0x11)
INSERT(ldc,0x12)
INSERT(ldc_w,0x13)
INSERT(ldc2_w,0x14)
INSERT(iload,0x15)
INSERT(lload,0x16)
INSERT(fload,0x17)
INSERT(dload,0x18)
INSERT(aload,0x19)
INSERT(iload_0,0x1a)
INSERT(iload_1,0x1b)
INSERT(iload_2,0x1c)
INSERT(iload_3,0x1d)
INSERT(lload_0,0x1e)
INSERT(lload_1,0x1f)
INSERT(lload_2,0x20)
INSERT(lload_3,0x21)
INSERT(fload_0,0x22)
INSERT(fload_1,0x23)
INSERT(fload_2,0x24)
INSERT(fload_3,0x25)
INSERT(dload_0,0x26)
INSERT(dload_1,0x27)
INSERT(dload_2,0x28)
INSERT(dload_3,0x29)
INSERT(aload_0,0x2a)
INSERT(aload_1,0x2b)
INSERT(aload_2,0x2c)
INSERT(aload_3,0x2d)
INSERT(iaload,0x2e)
INSERT(laload,0x2f)
INSERT(faload,0x30)
INSERT(daload,0x31)
INSERT(aaload,0x32)
INSERT(baload,0x33)
INSERT(caload,0x34)
INSERT(saload,0x35)
INSERT(istore,0x36)
INSERT(lstore,0x37)
INSERT(fstore,0x38)
INSERT(dstore,0x39)
INSERT(astore,0x3a)
INSERT(istore_0,0x3b)
INSERT(istore_1,0x3c)
INSERT(istore_2,0x3d)
INSERT(istore_3,0x3e)
INSERT(lstore_0,0x3f)
INSERT(lstore_1,0x40)
INSERT(lstore_2,0x41)
INSERT(lstore_3,0x42)
INSERT(fstore_0,0x43)
INSERT(fstore_1,0x44)
INSERT(fstore_2,0x45)
INSERT(fstore_3,0x46)
INSERT(dstore_0,0x47)
INSERT(dstore_1,0x48)
INSERT(dstore_2,0x49)
INSERT(dstore_3,0x4a)
INSERT(astore_0,0x4b)
INSERT(astore_1,0x4c)
INSERT(astore_2,0x4d)
INSERT(astore_3,0x4e)
INSERT(iastore,0x4f)
INSERT(lastore,0x50)
INSERT(fastore,0x51)
INSERT(dastore,0x52)
INSERT(aastore,0x53)
INSERT(bastore,0x54)
INSERT(castore,0x55)
INSERT(sastore,0x56)
INSERT(pop,0x57)
INSERT(pop2,0x58)
INSERT(dup,0x59)
INSERT(dup_x1,0x5a)
INSERT(dup_x2,0x5b)
INSERT(dup2,0x5c)
INSERT(dup2_x1,0x5d)
INSERT(dup2_x2,0x5e)
INSERT(swap,0x5f)
INSERT(iadd,0x60)
INSERT(ladd,0x61)
INSERT(fadd,0x62)
INSERT(dadd,0x63)
INSERT(isub,0x64)
INSERT(lsub,0x65)
INSERT(fsub,0x66)
INSERT(dsub,0x67)
INSERT(imul,0x68)
INSERT(lmul,0x69)
INSERT(fmul,0x6a)
INSERT(dmul,0x6b)
INSERT(idiv,0x6c)
INSERT(ldiv,0x6d)
INSERT(fdiv,0x6e)
INSERT(ddiv,0x6f)
INSERT(irem,0x70)
INSERT(lrem,0x71)
INSERT(frem,0x72)
INSERT(drem,0x73)
INSERT(ineg,0x74)
INSERT(lneg,0x75)
INSERT(fneg,0x76)
INSERT(dneg,0x77)
INSERT(ishl,0x78)
INSERT(lshl,0x79)
INSERT(ishr,0x7a)
INSERT(lshr,0x7b)
INSERT(iushr,0x7c)
INSERT(lushr,0x7d)
INSERT(iand,0x7e)
INSERT(land,0x7f)
INSERT(ior,0x80)
INSERT(lor,0x81)
INSERT(ixor,0x82)
INSERT(lxor,0x83)
INSERT(iinc,0x84)
INSERT(i2l,0x85)
INSERT(i2f,0x86)
INSERT(i2d,0x87)
INSERT(l2i,0x88)
INSERT(l2f,0x89)
INSERT(l2d,0x8a)
INSERT(f2i,0x8b)
INSERT(f2l,0x8c)
INSERT(f2d,0x8d)
INSERT(d2i,0x8e)
INSERT(d2l,0x8f)
INSERT(d2f,0x90)
INSERT(i2b,0x91)
INSERT(i2c,0x92)
INSERT(i2s,0x93)
INSERT(lcmp,0x94)
INSERT(fcmpl,0x95)
INSERT(fcmpg,0x96)
INSERT(dcmpl,0x97)
INSERT(dcmpg,0x98)
INSERT(ifeq,0x99)
INSERT(ifne,0x9a)
INSERT(iflt,0x9b)
INSERT(ifge,0x9c)
INSERT(ifgt,0x9d)
INSERT(ifle,0x9e)
INSERT(if_icmpeq,0x9f)
INSERT(if_icmpne,0xa0)
INSERT(if_icmplt,0xa1)
INSERT(if_icmpge,0xa2)
INSERT(if_icmpgt,0xa3)
INSERT(if_icmple,0xa4)
INSERT(if_acmpeq,0xa5)
INSERT(if_acmpne,0xa6)
INSERT(goto,0xa7)
INSERT(jsr,0xa8)
INSERT(ret,0xa9)
INSERT(tableswitch,0xaa)
INSERT(lookupswitch,0xab)
INSERT(ireturn,0xac)
INSERT(lreturn,0xad)
INSERT(freturn,0xae)
INSERT(dreturn,0xaf)
INSERT(areturn,0xb0)
INSERT(return,0xb1)
INSERT(getstatic,0xb2)
INSERT(putstatic,0xb3)
INSERT(getfield,0xb4)
INSERT(putfield,0xb5)
INSERT(invokevirtual,0xb6)
INSERT(invokespecial,0xb7)
INSERT(invokestatic,0xb8)
INSERT(invokeinterface,0xb9)
INSERT(xxxunusedxxx,0xba)
INSERT(new,0xbb)
INSERT(newarray,0xbc)
INSERT(anewarray,0xbd)
INSERT(arraylength,0xbe)
INSERT(athrow,0xbf)
INSERT(checkcast,0xc0)
INSERT(instanceof,0xc1)
INSERT(monitorenter,0xc2)
INSERT(monitorexit,0xc3)
INSERT(wide,0xc4)
INSERT(multianewarray,0xc5)
INSERT(ifnull,0xc6)
INSERT(ifnonnull,0xc7)
INSERT(goto_w,0xc8)
INSERT(jsr_w,0xc9)

INSERT(breakpoint,0xca)
INSERT(impdep1,0xfe)
INSERT(impdep2,0xff)
END_MAPPING(Opcode)